{
  "consumableRipName": "R.I.P",
  "consumableRipDescription": "永久销毁当前多格骨牌。",
  "consumableTrashcanName": "垃圾桶",
  "consumableTrashcanDescription": "增加 +3 次弃牌。",
  "consumableFeatherName": "羽毛",
  "consumableFeatherDescription": "让方块下落填满空隙，并清除已完成的行。",
  "consumableBombaName": "炸弹",
  "consumableBombaDescription": "清空整个网格并重新生成你的方块。",
  "consumableMorphName": "Morph",
  "consumableMorphDescription": "生成上次使用的消耗品。",
  "consumableLuckyBlockName": "幸运方块",
  "consumableLuckyBlockDescription": "生成 2 个随机消耗品。",
  "consumableMirrorName": "镜子",
  "consumableMirrorDescription": "复制当前多格骨牌并加入你的收藏。",
  "consumableLeafName": "叶子",
  "consumableLeafDescription": "降低负面方块出现的概率。",
  "consumableTrophyName": "奖杯",
  "consumableTrophyDescription": "获得一个随机永久升级。",
  "consumableBalloonName": "气球",
  "consumableBalloonDescription": "降低下落速度。",
  "consumableGumName": "口香糖",
  "consumableGumDescription": "填满非空行中的单个空隙，然后清除这些行。",
  "consumableHammerName": "锤子",
  "consumableHammerDescription": "找到最低的列高，并摧毁该高度以上的所有方块。",
  "consumableAxeName": "斧头",
  "consumableAxeDescription": "清除若干条随机的非空行。",
  "abilityGridShiftName": "网格移位",
  "abilityGridShiftDescription": "将每位玩家锁定的通道顺时针移动一格。",
  "consumableButterflyName": "蝴蝶",
  "consumableButterflyDescription": "将棋盘右半部分镜像到左半部分，并清除已完成的行。",
  "consumableLuckygonName": "Luckygon",
  "consumableLuckygonDescription": "将当前多格骨牌永久转换为幸运。",
  "consumableBrickgonName": "Brickgon",
  "consumableBrickgonDescription": "将当前多格骨牌永久转换为砖块。",
  "consumableCoggonName": "Coggon",
  "consumableCoggonDescription": "将当前多格骨牌永久转换为齿轮。",
  "consumableSlimegonName": "Slimegon",
  "consumableSlimegonDescription": "将当前多格骨牌永久转换为黏液。",
  "consumableMossgonName": "Mossgon",
  "consumableMossgonDescription": "将当前多格骨牌永久转换为苔藓。",
  "consumableHeartgonName": "Heartgon",
  "consumableHeartgonDescription": "将当前多格骨牌永久转换为爱心。",
  "consumableHoneygonName": "Honeygon",
  "consumableHoneygonDescription": "将当前多格骨牌永久转换为蜂巢。",
  "consumableTrashgonName": "Trashgon",
  "consumableTrashgonDescription": "将当前多格骨牌永久转换为垃圾。",
  "consumableBluegonName": "Bluegon",
  "consumableBluegonDescription": "将当前多格骨牌永久转换为蓝色。",
  "consumableGreengonName": "Greengon",
  "consumableGreengonDescription": "将当前多格骨牌永久转换为绿色。",
  "consumableOrangegonName": "Orangegon",
  "consumableOrangegonDescription": "将当前多格骨牌永久转换为橙色。",
  "consumableRedgonName": "Redgon",
  "consumableRedgonDescription": "将当前多格骨牌永久转换为红色。"
}
